index.py
k6_mcp_server-2.2.0.dist-info/METADATA
k6_mcp_server-2.2.0.dist-info/WHEEL
k6_mcp_server-2.2.0.dist-info/entry_points.txt
k6_mcp_server-2.2.0.dist-info/top_level.txt
k6_mcp_server-2.2.0.dist-info/RECORD
