Metadata-Version: 2.4
Name: k6-mcp-server
Version: 2.2.0
Summary: K6 Load Testing MCP Server for performance testing
Author-email: Hyeonggeun Oh <kandy@plaintexting.com>
License: MIT
Project-URL: Homepage, https://github.com/Geun-Oh/k6-mcp-server
Project-URL: Repository, https://github.com/Geun-Oh/k6-mcp-server
Project-URL: Issues, https://github.com/Geun-Oh/k6-mcp-server/issues
Keywords: k6,load-testing,performance,mcp,stress-testing
Classifier: Development Status :: 4 - Beta
Classifier: Intended Audience :: Developers
Classifier: License :: OSI Approved :: MIT License
Classifier: Programming Language :: Python :: 3
Classifier: Programming Language :: Python :: 3.10
Classifier: Programming Language :: Python :: 3.11
Classifier: Programming Language :: Python :: 3.12
Classifier: Topic :: Software Development :: Libraries :: Python Modules
Classifier: Topic :: System :: Systems Administration
Requires-Python: >=3.10
Requires-Dist: mcp>=1.0.0
